{
  "type": "Feature",
  "properties": {
    "iso:country":"US",
    "wof:name":"West Village",
    "wof:placetype":"neighbourhood"
},
  "geometry": {"coordinates":[-78.87980472603859,42.89190299305535],"type":"Point"}
}