{
  "type": "Feature",
  "properties": {
    "iso:country":"US",
    "wof:name":"Cedar Hill",
    "wof:placetype":"neighbourhood"
},
  "geometry": {"coordinates":[-72.89890717535407,41.32009270871791],"type":"Point"}
}